LICENSE
MANIFEST.in
README.md
requirements.txt
setup.cfg
setup.py
accounts/__init__.py
accounts/forms.py
accounts/settings.py
accounts/tokens.py
accounts/urls.py
accounts/views.py
accounts/locale/en/LC_MESSAGES/django.mo
accounts/locale/en/LC_MESSAGES/django.po
accounts/locale/ru/LC_MESSAGES/django.mo
accounts/locale/ru/LC_MESSAGES/django.po
accounts/locale/uk/LC_MESSAGES/django.mo
accounts/locale/uk/LC_MESSAGES/django.po
accounts/templates/accounts/base-email.html
accounts/templates/accounts/base-profile.html
accounts/templates/accounts/login.html
accounts/templates/accounts/password-change.html
accounts/templates/accounts/password-reset-confirm.html
accounts/templates/accounts/password-reset-email.html
accounts/templates/accounts/password-reset-subject.txt
accounts/templates/accounts/password-reset.html
accounts/templates/accounts/profile-change.html
accounts/templates/accounts/profile-remove.html
accounts/templates/accounts/profile.html
accounts/templates/accounts/signup-email.html
accounts/templates/accounts/signup-subject.txt
accounts/templates/accounts/signup.html
basement/__init__.py
basement/admin.py
basement/email.py
basement/fields.py
basement/forms.py
basement/manage.py
basement/middleware.py
basement/models.py
basement/services.py
basement/settings.py
basement/urls.py
basement/utils.py
basement/widgets.py
basement/http/__init__.py
basement/http/_exceptions.py
basement/http/_utils.py
basement/locale/ru/LC_MESSAGES/django.mo
basement/locale/ru/LC_MESSAGES/django.po
basement/locale/uk/LC_MESSAGES/django.mo
basement/locale/uk/LC_MESSAGES/django.po
basement/templates/email.html
basement/templates/modal.html
basement/templates/save-button-group.html
basement/templates/wrapper.html
basement/views/__init__.py
basement/views/_action_view.py
basement/views/_ajax_view.py
basement/views/_base_view.py
basement/views/_delete_view.py
basement/views/_download_db.py
basement/views/_filter_view.py
basement/views/_form_action_view.py
basement/views/_form_view.py
django_mp_basement.egg-info/PKG-INFO
django_mp_basement.egg-info/SOURCES.txt
django_mp_basement.egg-info/dependency_links.txt
django_mp_basement.egg-info/requires.txt
django_mp_basement.egg-info/top_level.txt
