Metadata-Version: 2.1
Name: django-mp-basement
Version: 4.0.0
Summary: Django basement app
Home-page: https://github.com/pmaigutyak/mp-basement
Author: Paul Maigutyak
Author-email: pmaigutyak@gmail.com
License: MIT
Download-URL: https://github.com/pmaigutyak/mp-basement/archive/4.0.0.tar.gz
Platform: UNKNOWN
License-File: LICENSE
